langchain_tilores/__init__.py
langchain_tilores/tilores_tools.py
langchain_tilores-0.3.0.dist-info/LICENSE
langchain_tilores-0.3.0.dist-info/METADATA
langchain_tilores-0.3.0.dist-info/WHEEL
langchain_tilores-0.3.0.dist-info/top_level.txt
langchain_tilores-0.3.0.dist-info/RECORD
